{
    "symbol": "XEL",
    "annualReports": [
        {
            "fiscalDateEnding": "2021-12-31",
            "reportedCurrency": "USD",
            "totalAssets": "57851000000",
            "totalCurrentAssets": "4239000000",
            "cashAndCashEquivalentsAtCarryingValue": "166000000",
            "cashAndShortTermInvestments": "166000000",
            "inventory": "631000000",
            "currentNetReceivables": "1018000000",
            "totalNonCurrentAssets": "50481000000",
            "propertyPlantEquipment": "45457000000",
            "accumulatedDepreciationAmortizationPPE": "17060000000",
            "intangibleAssets": "None",
            "intangibleAssetsExcludingGoodwill": "None",
            "goodwill": "None",
            "investments": "1047000000",
            "longTermInvestments": "372000000",
            "shortTermInvestments": "None",
            "otherCurrentAssets": "2424000000",
            "otherNonCurrrentAssets": "431000000",
            "totalLiabilities": "42239000000",
            "totalCurrentLiabilities": "5046000000",
            "currentAccountsPayable": "1409000000",
            "deferredRevenue": "196000000",
            "currentDebt": "1606000000",
            "shortTermDebt": "1005000000",
            "totalNonCurrentLiabilities": "37193000000",
            "capitalLeaseObligations": "69000000",
            "longTermDebt": "25830000000",
            "currentLongTermDebt": "598000000",
            "longTermDebtNoncurrent": "25232000000",
            "shortLongTermDebtTotal": "27107000000",
            "otherCurrentLiabilities": "459000000",
            "otherNonCurrentLiabilities": "158000000",
            "totalShareholderEquity": "15612000000",
            "treasuryStock": "None",
            "retainedEarnings": "6572000000",
            "commonStock": "1360000000",
            "commonStockSharesOutstanding": "544025269"
        },
        {
            "fiscalDateEnding": "2020-12-31",
            "reportedCurrency": "USD",
            "totalAssets": "53957000000",
            "totalCurrentAssets": "3275000000",
            "cashAndCashEquivalentsAtCarryingValue": "129000000",
            "cashAndShortTermInvestments": "129000000",
            "inventory": "535000000",
            "currentNetReceivables": "916000000",
            "totalNonCurrentAssets": "48037000000",
            "propertyPlantEquipment": "42950000000",
            "accumulatedDepreciationAmortizationPPE": "16657000000",
            "intangibleAssets": "None",
            "intangibleAssetsExcludingGoodwill": "None",
            "goodwill": "None",
            "investments": "904000000",
            "longTermInvestments": "319000000",
            "shortTermInvestments": "3096000000",
            "otherCurrentAssets": "981000000",
            "otherNonCurrrentAssets": "379000000",
            "totalLiabilities": "39382000000",
            "totalCurrentLiabilities": "4239000000",
            "currentAccountsPayable": "1237000000",
            "deferredRevenue": "197000000",
            "currentDebt": "1005000000",
            "shortTermDebt": "584000000",
            "totalNonCurrentLiabilities": "35143000000",
            "capitalLeaseObligations": "73000000",
            "longTermDebt": "20066000000",
            "currentLongTermDebt": "417000000",
            "longTermDebtNoncurrent": "24412000000",
            "shortLongTermDebtTotal": "20650000000",
            "otherCurrentLiabilities": "407000000",
            "otherNonCurrentLiabilities": "183000000",
            "totalShareholderEquity": "14575000000",
            "treasuryStock": "None",
            "retainedEarnings": "5968000000",
            "commonStock": "1344000000",
            "commonStockSharesOutstanding": "537438394"
        },
        {
            "fiscalDateEnding": "2019-12-31",
            "reportedCurrency": "USD",
            "totalAssets": "50448000000",
            "totalCurrentAssets": "3113000000",
            "cashAndCashEquivalentsAtCarryingValue": "248000000",
            "cashAndShortTermInvestments": "248000000",
            "inventory": "544000000",
            "currentNetReceivables": "837000000",
            "totalNonCurrentAssets": "45034000000",
            "propertyPlantEquipment": "39483000000",
            "accumulatedDepreciationAmortizationPPE": "16735000000",
            "intangibleAssets": "None",
            "intangibleAssetsExcludingGoodwill": "None",
            "goodwill": "None",
            "investments": "799000000",
            "longTermInvestments": "291000000",
            "shortTermInvestments": "None",
            "otherCurrentAssets": "771000000",
            "otherNonCurrrentAssets": "492000000",
            "totalLiabilities": "37209000000",
            "totalCurrentLiabilities": "4568000000",
            "currentAccountsPayable": "1294000000",
            "deferredRevenue": "203000000",
            "currentDebt": "1297000000",
            "shortTermDebt": "595000000",
            "totalNonCurrentLiabilities": "32641000000",
            "capitalLeaseObligations": "77000000",
            "longTermDebt": "18109000000",
            "currentLongTermDebt": "698000000",
            "longTermDebtNoncurrent": "20227000000",
            "shortLongTermDebtTotal": "18704000000",
            "otherCurrentLiabilities": "468000000",
            "otherNonCurrentLiabilities": "186000000",
            "totalShareholderEquity": "13239000000",
            "treasuryStock": "None",
            "retainedEarnings": "5413000000",
            "commonStock": "1311000000",
            "commonStockSharesOutstanding": "524539000"
        },
        {
            "fiscalDateEnding": "2018-12-31",
            "reportedCurrency": "USD",
            "totalAssets": "45987000000",
            "totalCurrentAssets": "3094000000",
            "cashAndCashEquivalentsAtCarryingValue": "147000000",
            "cashAndShortTermInvestments": "147000000",
            "inventory": "548000000",
            "currentNetReceivables": "860000000",
            "totalNonCurrentAssets": "40838000000",
            "propertyPlantEquipment": "36944000000",
            "accumulatedDepreciationAmortizationPPE": "15659000000",
            "intangibleAssets": "None",
            "intangibleAssetsExcludingGoodwill": "None",
            "goodwill": "None",
            "investments": "698000000",
            "longTermInvestments": "262000000",
            "shortTermInvestments": "None",
            "otherCurrentAssets": "784000000",
            "otherNonCurrrentAssets": "272000000",
            "totalLiabilities": "33765000000",
            "totalCurrentLiabilities": "4460000000",
            "currentAccountsPayable": "1237000000",
            "deferredRevenue": "None",
            "currentDebt": "1444000000",
            "shortTermDebt": "1038000000",
            "totalNonCurrentLiabilities": "29305000000",
            "capitalLeaseObligations": "None",
            "longTermDebt": "16209000000",
            "currentLongTermDebt": "406000000",
            "longTermDebtNoncurrent": "16755000000",
            "shortLongTermDebtTotal": "17247000000",
            "otherCurrentLiabilities": "463000000",
            "otherNonCurrentLiabilities": "206000000",
            "totalShareholderEquity": "12222000000",
            "treasuryStock": "None",
            "retainedEarnings": "4893000000",
            "commonStock": "1285000000",
            "commonStockSharesOutstanding": "514036787"
        },
        {
            "fiscalDateEnding": "2017-12-31",
            "reportedCurrency": "USD",
            "totalAssets": "43030000000",
            "totalCurrentAssets": "2973000000",
            "cashAndCashEquivalentsAtCarryingValue": "83000000",
            "cashAndShortTermInvestments": "83000000",
            "inventory": "610000000",
            "currentNetReceivables": "797000000",
            "totalNonCurrentAssets": "37914000000",
            "propertyPlantEquipment": "34329000000",
            "accumulatedDepreciationAmortizationPPE": "15000000000",
            "intangibleAssets": "None",
            "intangibleAssetsExcludingGoodwill": "None",
            "goodwill": "None",
            "investments": "695000000",
            "longTermInvestments": "254000000",
            "shortTermInvestments": "None",
            "otherCurrentAssets": "719000000",
            "otherNonCurrrentAssets": "278000000",
            "totalLiabilities": "31575000000",
            "totalCurrentLiabilities": "4088000000",
            "currentAccountsPayable": "1243000000",
            "deferredRevenue": "None",
            "currentDebt": "1271000000",
            "shortTermDebt": "814000000",
            "totalNonCurrentLiabilities": "27487000000",
            "capitalLeaseObligations": "None",
            "longTermDebt": "3329000000",
            "currentLongTermDebt": "457000000",
            "longTermDebtNoncurrent": "None",
            "shortLongTermDebtTotal": "4143000000",
            "otherCurrentLiabilities": "501000000",
            "otherNonCurrentLiabilities": "145000000",
            "totalShareholderEquity": "11455000000",
            "treasuryStock": "None",
            "retainedEarnings": "4413000000",
            "commonStock": "1269000000",
            "commonStockSharesOutstanding": "507762881"
        }
    ],
    "quarterlyReports": [
        {
            "fiscalDateEnding": "2021-12-31",
            "reportedCurrency": "USD",
            "totalAssets": "57851000000",
            "totalCurrentAssets": "4239000000",
            "cashAndCashEquivalentsAtCarryingValue": "166000000",
            "cashAndShortTermInvestments": "166000000",
            "inventory": "631000000",
            "currentNetReceivables": "1018000000",
            "totalNonCurrentAssets": "50481000000",
            "propertyPlantEquipment": "45457000000",
            "accumulatedDepreciationAmortizationPPE": "17060000000",
            "intangibleAssets": "None",
            "intangibleAssetsExcludingGoodwill": "None",
            "goodwill": "None",
            "investments": "1047000000",
            "longTermInvestments": "372000000",
            "shortTermInvestments": "None",
            "otherCurrentAssets": "2424000000",
            "otherNonCurrrentAssets": "431000000",
            "totalLiabilities": "42239000000",
            "totalCurrentLiabilities": "5046000000",
            "currentAccountsPayable": "1409000000",
            "deferredRevenue": "196000000",
            "currentDebt": "1606000000",
            "shortTermDebt": "1005000000",
            "totalNonCurrentLiabilities": "37193000000",
            "capitalLeaseObligations": "69000000",
            "longTermDebt": "25830000000",
            "currentLongTermDebt": "598000000",
            "longTermDebtNoncurrent": "25232000000",
            "shortLongTermDebtTotal": "27107000000",
            "otherCurrentLiabilities": "459000000",
            "otherNonCurrentLiabilities": "158000000",
            "totalShareholderEquity": "15612000000",
            "treasuryStock": "None",
            "retainedEarnings": "6572000000",
            "commonStock": "1360000000",
            "commonStockSharesOutstanding": "544025269"
        },
        {
            "fiscalDateEnding": "2021-09-30",
            "reportedCurrency": "USD",
            "totalAssets": "57517000000",
            "totalCurrentAssets": "4487000000",
            "cashAndCashEquivalentsAtCarryingValue": "631000000",
            "cashAndShortTermInvestments": "631000000",
            "inventory": "587000000",
            "currentNetReceivables": "1022000000",
            "totalNonCurrentAssets": "49946000000",
            "propertyPlantEquipment": "44730000000",
            "accumulatedDepreciationAmortizationPPE": "17711000000",
            "intangibleAssets": "None",
            "intangibleAssetsExcludingGoodwill": "None",
            "goodwill": "None",
            "investments": "1020000000",
            "longTermInvestments": "362000000",
            "shortTermInvestments": "3446000000",
            "otherCurrentAssets": "1591000000",
            "otherNonCurrrentAssets": "339000000",
            "totalLiabilities": "42346000000",
            "totalCurrentLiabilities": "5764000000",
            "currentAccountsPayable": "1319000000",
            "deferredRevenue": "199000000",
            "currentDebt": "2368000000",
            "shortTermDebt": "1747000000",
            "totalNonCurrentLiabilities": "36582000000",
            "capitalLeaseObligations": "70000000",
            "longTermDebt": "21600000000",
            "currentLongTermDebt": "618000000",
            "longTermDebtNoncurrent": "24657000000",
            "shortLongTermDebtTotal": "23347000000",
            "otherCurrentLiabilities": "440000000",
            "otherNonCurrentLiabilities": "207000000",
            "totalShareholderEquity": "15171000000",
            "treasuryStock": "None",
            "retainedEarnings": "6508000000",
            "commonStock": "1346000000",
            "commonStockSharesOutstanding": "538458952"
        },
        {
            "fiscalDateEnding": "2021-06-30",
            "reportedCurrency": "USD",
            "totalAssets": "56779000000",
            "totalCurrentAssets": "4147000000",
            "cashAndCashEquivalentsAtCarryingValue": "538000000",
            "cashAndShortTermInvestments": "538000000",
            "inventory": "500000000",
            "currentNetReceivables": "948000000",
            "totalNonCurrentAssets": "49594000000",
            "propertyPlantEquipment": "44141000000",
            "accumulatedDepreciationAmortizationPPE": "17382000000",
            "intangibleAssets": "None",
            "intangibleAssetsExcludingGoodwill": "None",
            "goodwill": "None",
            "investments": "1008000000",
            "longTermInvestments": "351000000",
            "shortTermInvestments": "3389000000",
            "otherCurrentAssets": "1462000000",
            "otherNonCurrrentAssets": "395000000",
            "totalLiabilities": "41987000000",
            "totalCurrentLiabilities": "4950000000",
            "currentAccountsPayable": "1273000000",
            "deferredRevenue": "196000000",
            "currentDebt": "1766000000",
            "shortTermDebt": "1745000000",
            "totalNonCurrentLiabilities": "37037000000",
            "capitalLeaseObligations": "71000000",
            "longTermDebt": "21497000000",
            "currentLongTermDebt": "18000000",
            "longTermDebtNoncurrent": "24686000000",
            "shortLongTermDebtTotal": "23242000000",
            "otherCurrentLiabilities": "409000000",
            "otherNonCurrentLiabilities": "208000000",
            "totalShareholderEquity": "14792000000",
            "treasuryStock": "None",
            "retainedEarnings": "6146000000",
            "commonStock": "1346000000",
            "commonStockSharesOutstanding": "538305927"
        },
        {
            "fiscalDateEnding": "2021-03-31",
            "reportedCurrency": "USD",
            "totalAssets": "56511000000",
            "totalCurrentAssets": "4315000000",
            "cashAndCashEquivalentsAtCarryingValue": "1039000000",
            "cashAndShortTermInvestments": "1039000000",
            "inventory": "469000000",
            "currentNetReceivables": "959000000",
            "totalNonCurrentAssets": "49371000000",
            "propertyPlantEquipment": "43582000000",
            "accumulatedDepreciationAmortizationPPE": "17060000000",
            "intangibleAssets": "None",
            "intangibleAssetsExcludingGoodwill": "None",
            "goodwill": "None",
            "investments": "915000000",
            "longTermInvestments": "329000000",
            "shortTermInvestments": "3154000000",
            "otherCurrentAssets": "1257000000",
            "otherNonCurrrentAssets": "409000000",
            "totalLiabilities": "41811000000",
            "totalCurrentLiabilities": "4877000000",
            "currentAccountsPayable": "1213000000",
            "deferredRevenue": "195000000",
            "currentDebt": "1498000000",
            "shortTermDebt": "1477000000",
            "totalNonCurrentLiabilities": "36934000000",
            "capitalLeaseObligations": "71000000",
            "longTermDebt": "21491000000",
            "currentLongTermDebt": "17000000",
            "longTermDebtNoncurrent": "23654000000",
            "shortLongTermDebtTotal": "22968000000",
            "otherCurrentLiabilities": "370000000",
            "otherNonCurrentLiabilities": "225000000",
            "totalShareholderEquity": "14700000000",
            "treasuryStock": "None",
            "retainedEarnings": "6082000000",
            "commonStock": "1345000000",
            "commonStockSharesOutstanding": "538076662"
        },
        {
            "fiscalDateEnding": "2020-12-31",
            "reportedCurrency": "USD",
            "totalAssets": "53957000000",
            "totalCurrentAssets": "3275000000",
            "cashAndCashEquivalentsAtCarryingValue": "129000000",
            "cashAndShortTermInvestments": "129000000",
            "inventory": "535000000",
            "currentNetReceivables": "916000000",
            "totalNonCurrentAssets": "48037000000",
            "propertyPlantEquipment": "42950000000",
            "accumulatedDepreciationAmortizationPPE": "16657000000",
            "intangibleAssets": "None",
            "intangibleAssetsExcludingGoodwill": "None",
            "goodwill": "None",
            "investments": "904000000",
            "longTermInvestments": "319000000",
            "shortTermInvestments": "3096000000",
            "otherCurrentAssets": "981000000",
            "otherNonCurrrentAssets": "379000000",
            "totalLiabilities": "39382000000",
            "totalCurrentLiabilities": "4239000000",
            "currentAccountsPayable": "1237000000",
            "deferredRevenue": "197000000",
            "currentDebt": "1005000000",
            "shortTermDebt": "584000000",
            "totalNonCurrentLiabilities": "35143000000",
            "capitalLeaseObligations": "73000000",
            "longTermDebt": "20066000000",
            "currentLongTermDebt": "417000000",
            "longTermDebtNoncurrent": "24412000000",
            "shortLongTermDebtTotal": "20650000000",
            "otherCurrentLiabilities": "407000000",
            "otherNonCurrentLiabilities": "183000000",
            "totalShareholderEquity": "14575000000",
            "treasuryStock": "None",
            "retainedEarnings": "5968000000",
            "commonStock": "1344000000",
            "commonStockSharesOutstanding": "537438394"
        },
        {
            "fiscalDateEnding": "2020-09-30",
            "reportedCurrency": "USD",
            "totalAssets": "53708000000",
            "totalCurrentAssets": "3837000000",
            "cashAndCashEquivalentsAtCarryingValue": "885000000",
            "cashAndShortTermInvestments": "885000000",
            "inventory": "512000000",
            "currentNetReceivables": "899000000",
            "totalNonCurrentAssets": "47350000000",
            "propertyPlantEquipment": "42227000000",
            "accumulatedDepreciationAmortizationPPE": "17456000000",
            "intangibleAssets": "None",
            "intangibleAssetsExcludingGoodwill": "None",
            "goodwill": "None",
            "investments": "851000000",
            "longTermInvestments": "292000000",
            "shortTermInvestments": "2813000000",
            "otherCurrentAssets": "955000000",
            "otherNonCurrrentAssets": "348000000",
            "totalLiabilities": "39931000000",
            "totalCurrentLiabilities": "4393000000",
            "currentAccountsPayable": "1602000000",
            "deferredRevenue": "201000000",
            "currentDebt": "901000000",
            "shortTermDebt": "500000000",
            "totalNonCurrentLiabilities": "35538000000",
            "capitalLeaseObligations": "1603000000",
            "longTermDebt": "20361000000",
            "currentLongTermDebt": "401000000",
            "longTermDebtNoncurrent": "24396000000",
            "shortLongTermDebtTotal": "20861000000",
            "otherCurrentLiabilities": "416000000",
            "otherNonCurrentLiabilities": "178000000",
            "totalShareholderEquity": "13777000000",
            "treasuryStock": "None",
            "retainedEarnings": "5912000000",
            "commonStock": "1314000000",
            "commonStockSharesOutstanding": "525452824"
        },
        {
            "fiscalDateEnding": "2020-06-30",
            "reportedCurrency": "USD",
            "totalAssets": "53456000000",
            "totalCurrentAssets": "4390000000",
            "cashAndCashEquivalentsAtCarryingValue": "1625000000",
            "cashAndShortTermInvestments": "1625000000",
            "inventory": "487000000",
            "currentNetReceivables": "799000000",
            "totalNonCurrentAssets": "46671000000",
            "propertyPlantEquipment": "41124000000",
            "accumulatedDepreciationAmortizationPPE": "17097000000",
            "intangibleAssets": "None",
            "intangibleAssetsExcludingGoodwill": "None",
            "goodwill": "None",
            "investments": "829000000",
            "longTermInvestments": "288000000",
            "shortTermInvestments": "None",
            "otherCurrentAssets": "866000000",
            "otherNonCurrrentAssets": "1019000000",
            "totalLiabilities": "40071000000",
            "totalCurrentLiabilities": "5473000000",
            "currentAccountsPayable": "1188000000",
            "deferredRevenue": "201000000",
            "currentDebt": "2511000000",
            "shortTermDebt": "1410000000",
            "totalNonCurrentLiabilities": "34598000000",
            "capitalLeaseObligations": "1274000000",
            "longTermDebt": "20564000000",
            "currentLongTermDebt": "1101000000",
            "longTermDebtNoncurrent": "24327000000",
            "shortLongTermDebtTotal": "21974000000",
            "otherCurrentLiabilities": "396000000",
            "otherNonCurrentLiabilities": "185000000",
            "totalShareholderEquity": "13385000000",
            "treasuryStock": "None",
            "retainedEarnings": "5538000000",
            "commonStock": "1313000000",
            "commonStockSharesOutstanding": "525204978"
        },
        {
            "fiscalDateEnding": "2020-03-31",
            "reportedCurrency": "USD",
            "totalAssets": "51133000000",
            "totalCurrentAssets": "2983000000",
            "cashAndCashEquivalentsAtCarryingValue": "244000000",
            "cashAndShortTermInvestments": "244000000",
            "inventory": "488000000",
            "currentNetReceivables": "839000000",
            "totalNonCurrentAssets": "46008000000",
            "propertyPlantEquipment": "40776000000",
            "accumulatedDepreciationAmortizationPPE": "16730000000",
            "intangibleAssets": "None",
            "intangibleAssetsExcludingGoodwill": "None",
            "goodwill": "None",
            "investments": "788000000",
            "longTermInvestments": "287000000",
            "shortTermInvestments": "None",
            "otherCurrentAssets": "851000000",
            "otherNonCurrrentAssets": "516000000",
            "totalLiabilities": "37831000000",
            "totalCurrentLiabilities": "5839000000",
            "currentAccountsPayable": "996000000",
            "deferredRevenue": "202000000",
            "currentDebt": "2867000000",
            "shortTermDebt": "1765000000",
            "totalNonCurrentLiabilities": "31992000000",
            "capitalLeaseObligations": "1306000000",
            "longTermDebt": "18112000000",
            "currentLongTermDebt": "1102000000",
            "longTermDebtNoncurrent": "19864000000",
            "shortLongTermDebtTotal": "19877000000",
            "otherCurrentLiabilities": "379000000",
            "otherNonCurrentLiabilities": "196000000",
            "totalShareholderEquity": "13302000000",
            "treasuryStock": "None",
            "retainedEarnings": "5478000000",
            "commonStock": "1313000000",
            "commonStockSharesOutstanding": "525033594"
        },
        {
            "fiscalDateEnding": "2019-12-31",
            "reportedCurrency": "USD",
            "totalAssets": "50448000000",
            "totalCurrentAssets": "3113000000",
            "cashAndCashEquivalentsAtCarryingValue": "248000000",
            "cashAndShortTermInvestments": "248000000",
            "inventory": "544000000",
            "currentNetReceivables": "837000000",
            "totalNonCurrentAssets": "45034000000",
            "propertyPlantEquipment": "39483000000",
            "accumulatedDepreciationAmortizationPPE": "16735000000",
            "intangibleAssets": "None",
            "intangibleAssetsExcludingGoodwill": "None",
            "goodwill": "None",
            "investments": "799000000",
            "longTermInvestments": "291000000",
            "shortTermInvestments": "None",
            "otherCurrentAssets": "771000000",
            "otherNonCurrrentAssets": "492000000",
            "totalLiabilities": "37209000000",
            "totalCurrentLiabilities": "4568000000",
            "currentAccountsPayable": "1294000000",
            "deferredRevenue": "203000000",
            "currentDebt": "1297000000",
            "shortTermDebt": "595000000",
            "totalNonCurrentLiabilities": "32641000000",
            "capitalLeaseObligations": "77000000",
            "longTermDebt": "18109000000",
            "currentLongTermDebt": "698000000",
            "longTermDebtNoncurrent": "20227000000",
            "shortLongTermDebtTotal": "18704000000",
            "otherCurrentLiabilities": "468000000",
            "otherNonCurrentLiabilities": "186000000",
            "totalShareholderEquity": "13239000000",
            "treasuryStock": "None",
            "retainedEarnings": "5413000000",
            "commonStock": "1311000000",
            "commonStockSharesOutstanding": "524539000"
        },
        {
            "fiscalDateEnding": "2019-09-30",
            "reportedCurrency": "USD",
            "totalAssets": "50240000000",
            "totalCurrentAssets": "3600000000",
            "cashAndCashEquivalentsAtCarryingValue": "864000000",
            "cashAndShortTermInvestments": "864000000",
            "inventory": "544000000",
            "currentNetReceivables": "821000000",
            "totalNonCurrentAssets": "44465000000",
            "propertyPlantEquipment": "38703000000",
            "accumulatedDepreciationAmortizationPPE": "16549000000",
            "intangibleAssets": "None",
            "intangibleAssetsExcludingGoodwill": "None",
            "goodwill": "None",
            "investments": "779000000",
            "longTermInvestments": "283000000",
            "shortTermInvestments": "None",
            "otherCurrentAssets": "748000000",
            "otherNonCurrrentAssets": "478000000",
            "totalLiabilities": "37099000000",
            "totalCurrentLiabilities": "5021000000",
            "currentAccountsPayable": "1258000000",
            "deferredRevenue": "None",
            "currentDebt": "1786000000",
            "shortTermDebt": "933000000",
            "totalNonCurrentLiabilities": "32078000000",
            "capitalLeaseObligations": "78000000",
            "longTermDebt": "17672000000",
            "currentLongTermDebt": "849000000",
            "longTermDebtNoncurrent": "20064000000",
            "shortLongTermDebtTotal": "18605000000",
            "otherCurrentLiabilities": "614000000",
            "otherNonCurrentLiabilities": "186000000",
            "totalShareholderEquity": "13141000000",
            "treasuryStock": "None",
            "retainedEarnings": "5336000000",
            "commonStock": "1311000000",
            "commonStockSharesOutstanding": "514865476"
        },
        {
            "fiscalDateEnding": "2019-06-30",
            "reportedCurrency": "USD",
            "totalAssets": "48584000000",
            "totalCurrentAssets": "2939000000",
            "cashAndCashEquivalentsAtCarryingValue": "353000000",
            "cashAndShortTermInvestments": "353000000",
            "inventory": "483000000",
            "currentNetReceivables": "737000000",
            "totalNonCurrentAssets": "43485000000",
            "propertyPlantEquipment": "37651000000",
            "accumulatedDepreciationAmortizationPPE": "16278000000",
            "intangibleAssets": "None",
            "intangibleAssetsExcludingGoodwill": "None",
            "goodwill": "None",
            "investments": "758000000",
            "longTermInvestments": "271000000",
            "shortTermInvestments": "None",
            "otherCurrentAssets": "727000000",
            "otherNonCurrrentAssets": "490000000",
            "totalLiabilities": "36218000000",
            "totalCurrentLiabilities": "5060000000",
            "currentAccountsPayable": "1057000000",
            "deferredRevenue": "None",
            "currentDebt": "2150000000",
            "shortTermDebt": "1597000000",
            "totalNonCurrentLiabilities": "31158000000",
            "capitalLeaseObligations": "79000000",
            "longTermDebt": "15996000000",
            "currentLongTermDebt": "549000000",
            "longTermDebtNoncurrent": "None",
            "shortLongTermDebtTotal": "1597000000",
            "otherCurrentLiabilities": "614000000",
            "otherNonCurrentLiabilities": "190000000",
            "totalShareholderEquity": "12366000000",
            "treasuryStock": "None",
            "retainedEarnings": "5024000000",
            "commonStock": "1287000000",
            "commonStockSharesOutstanding": "514865476"
        },
        {
            "fiscalDateEnding": "2019-03-31",
            "reportedCurrency": "USD",
            "totalAssets": "47850000000",
            "totalCurrentAssets": "2909000000",
            "cashAndCashEquivalentsAtCarryingValue": "94000000",
            "cashAndShortTermInvestments": "94000000",
            "inventory": "445000000",
            "currentNetReceivables": "974000000",
            "totalNonCurrentAssets": "41083000000",
            "propertyPlantEquipment": "37114000000",
            "accumulatedDepreciationAmortizationPPE": "15961000000",
            "intangibleAssets": "None",
            "intangibleAssetsExcludingGoodwill": "None",
            "goodwill": "None",
            "investments": "745000000",
            "longTermInvestments": "265000000",
            "shortTermInvestments": "None",
            "otherCurrentAssets": "734000000",
            "otherNonCurrrentAssets": "499000000",
            "totalLiabilities": "35521000000",
            "totalCurrentLiabilities": "4424000000",
            "currentAccountsPayable": "1154000000",
            "deferredRevenue": "None",
            "currentDebt": "1254000000",
            "shortTermDebt": "1252000000",
            "totalNonCurrentLiabilities": "31097000000",
            "capitalLeaseObligations": "80000000",
            "longTermDebt": "16118000000",
            "currentLongTermDebt": "1254000000",
            "longTermDebtNoncurrent": "None",
            "shortLongTermDebtTotal": "1252000000",
            "otherCurrentLiabilities": "549000000",
            "otherNonCurrentLiabilities": "212000000",
            "totalShareholderEquity": "12329000000",
            "treasuryStock": "None",
            "retainedEarnings": "4996000000",
            "commonStock": "1287000000",
            "commonStockSharesOutstanding": "514667625"
        },
        {
            "fiscalDateEnding": "2018-12-31",
            "reportedCurrency": "USD",
            "totalAssets": "45987000000",
            "totalCurrentAssets": "3094000000",
            "cashAndCashEquivalentsAtCarryingValue": "147000000",
            "cashAndShortTermInvestments": "147000000",
            "inventory": "548000000",
            "currentNetReceivables": "860000000",
            "totalNonCurrentAssets": "40838000000",
            "propertyPlantEquipment": "36944000000",
            "accumulatedDepreciationAmortizationPPE": "15659000000",
            "intangibleAssets": "None",
            "intangibleAssetsExcludingGoodwill": "None",
            "goodwill": "None",
            "investments": "698000000",
            "longTermInvestments": "262000000",
            "shortTermInvestments": "None",
            "otherCurrentAssets": "784000000",
            "otherNonCurrrentAssets": "272000000",
            "totalLiabilities": "33765000000",
            "totalCurrentLiabilities": "4460000000",
            "currentAccountsPayable": "1237000000",
            "deferredRevenue": "None",
            "currentDebt": "1444000000",
            "shortTermDebt": "1038000000",
            "totalNonCurrentLiabilities": "29305000000",
            "capitalLeaseObligations": "None",
            "longTermDebt": "16209000000",
            "currentLongTermDebt": "406000000",
            "longTermDebtNoncurrent": "16755000000",
            "shortLongTermDebtTotal": "17247000000",
            "otherCurrentLiabilities": "463000000",
            "otherNonCurrentLiabilities": "206000000",
            "totalShareholderEquity": "12222000000",
            "treasuryStock": "None",
            "retainedEarnings": "4893000000",
            "commonStock": "1285000000",
            "commonStockSharesOutstanding": "514036787"
        },
        {
            "fiscalDateEnding": "2018-09-30",
            "reportedCurrency": "USD",
            "totalAssets": "44835000000",
            "totalCurrentAssets": "3003000000",
            "cashAndCashEquivalentsAtCarryingValue": "213000000",
            "cashAndShortTermInvestments": "213000000",
            "inventory": "528000000",
            "currentNetReceivables": "856000000",
            "totalNonCurrentAssets": "39621000000",
            "propertyPlantEquipment": "35879000000",
            "accumulatedDepreciationAmortizationPPE": "15483000000",
            "intangibleAssets": "None",
            "intangibleAssetsExcludingGoodwill": "None",
            "goodwill": "None",
            "investments": "720000000",
            "longTermInvestments": "262000000",
            "shortTermInvestments": "None",
            "otherCurrentAssets": "756000000",
            "otherNonCurrrentAssets": "272000000",
            "totalLiabilities": "32670000000",
            "totalCurrentLiabilities": "3838000000",
            "currentAccountsPayable": "1189000000",
            "deferredRevenue": "None",
            "currentDebt": "993000000",
            "shortTermDebt": "437000000",
            "totalNonCurrentLiabilities": "28832000000",
            "capitalLeaseObligations": "None",
            "longTermDebt": "15508000000",
            "currentLongTermDebt": "556000000",
            "longTermDebtNoncurrent": "None",
            "shortLongTermDebtTotal": "437000000",
            "otherCurrentLiabilities": "435000000",
            "otherNonCurrentLiabilities": "202000000",
            "totalShareholderEquity": "12165000000",
            "treasuryStock": "None",
            "retainedEarnings": "4876000000",
            "commonStock": "1283000000",
            "commonStockSharesOutstanding": "513298952"
        },
        {
            "fiscalDateEnding": "2018-06-30",
            "reportedCurrency": "USD",
            "totalAssets": "44240000000",
            "totalCurrentAssets": "3056000000",
            "cashAndCashEquivalentsAtCarryingValue": "332000000",
            "cashAndShortTermInvestments": "332000000",
            "inventory": "511000000",
            "currentNetReceivables": "808000000",
            "totalNonCurrentAssets": "39039000000",
            "propertyPlantEquipment": "35289000000",
            "accumulatedDepreciationAmortizationPPE": "15479000000",
            "intangibleAssets": "None",
            "intangibleAssetsExcludingGoodwill": "None",
            "goodwill": "None",
            "investments": "707000000",
            "longTermInvestments": "253000000",
            "shortTermInvestments": "None",
            "otherCurrentAssets": "757000000",
            "otherNonCurrrentAssets": "273000000",
            "totalLiabilities": "32590000000",
            "totalCurrentLiabilities": "4178000000",
            "currentAccountsPayable": "1092000000",
            "deferredRevenue": "None",
            "currentDebt": "1538000000",
            "shortTermDebt": "682000000",
            "totalNonCurrentLiabilities": "28412000000",
            "capitalLeaseObligations": "None",
            "longTermDebt": "15311000000",
            "currentLongTermDebt": "856000000",
            "longTermDebtNoncurrent": "None",
            "shortLongTermDebtTotal": "682000000",
            "otherCurrentLiabilities": "441000000",
            "otherNonCurrentLiabilities": "226000000",
            "totalShareholderEquity": "11650000000",
            "treasuryStock": "None",
            "retainedEarnings": "4580000000",
            "commonStock": "1272000000",
            "commonStockSharesOutstanding": "508898420"
        },
        {
            "fiscalDateEnding": "2018-03-31",
            "reportedCurrency": "USD",
            "totalAssets": "43159000000",
            "totalCurrentAssets": "2782000000",
            "cashAndCashEquivalentsAtCarryingValue": "116000000",
            "cashAndShortTermInvestments": "116000000",
            "inventory": "492000000",
            "currentNetReceivables": "868000000",
            "totalNonCurrentAssets": "38231000000",
            "propertyPlantEquipment": "34679000000",
            "accumulatedDepreciationAmortizationPPE": "15276000000",
            "intangibleAssets": "None",
            "intangibleAssetsExcludingGoodwill": "None",
            "goodwill": "None",
            "investments": "709000000",
            "longTermInvestments": "258000000",
            "shortTermInvestments": "None",
            "otherCurrentAssets": "701000000",
            "otherNonCurrrentAssets": "280000000",
            "totalLiabilities": "31598000000",
            "totalCurrentLiabilities": "4122000000",
            "currentAccountsPayable": "1027000000",
            "deferredRevenue": "None",
            "currentDebt": "1482000000",
            "shortTermDebt": "1025000000",
            "totalNonCurrentLiabilities": "27476000000",
            "capitalLeaseObligations": "None",
            "longTermDebt": "14522000000",
            "currentLongTermDebt": "457000000",
            "longTermDebtNoncurrent": "None",
            "shortLongTermDebtTotal": "1025000000",
            "otherCurrentLiabilities": "429000000",
            "otherNonCurrentLiabilities": "143000000",
            "totalShareholderEquity": "11561000000",
            "treasuryStock": "None",
            "retainedEarnings": "4510000000",
            "commonStock": "1272000000",
            "commonStockSharesOutstanding": "508661859"
        },
        {
            "fiscalDateEnding": "2017-12-31",
            "reportedCurrency": "USD",
            "totalAssets": "43030000000",
            "totalCurrentAssets": "2973000000",
            "cashAndCashEquivalentsAtCarryingValue": "83000000",
            "cashAndShortTermInvestments": "83000000",
            "inventory": "610000000",
            "currentNetReceivables": "797000000",
            "totalNonCurrentAssets": "37914000000",
            "propertyPlantEquipment": "34329000000",
            "accumulatedDepreciationAmortizationPPE": "15000000000",
            "intangibleAssets": "None",
            "intangibleAssetsExcludingGoodwill": "None",
            "goodwill": "None",
            "investments": "695000000",
            "longTermInvestments": "254000000",
            "shortTermInvestments": "None",
            "otherCurrentAssets": "719000000",
            "otherNonCurrrentAssets": "278000000",
            "totalLiabilities": "31575000000",
            "totalCurrentLiabilities": "4088000000",
            "currentAccountsPayable": "1243000000",
            "deferredRevenue": "None",
            "currentDebt": "1271000000",
            "shortTermDebt": "814000000",
            "totalNonCurrentLiabilities": "27487000000",
            "capitalLeaseObligations": "None",
            "longTermDebt": "3329000000",
            "currentLongTermDebt": "457000000",
            "longTermDebtNoncurrent": "None",
            "shortLongTermDebtTotal": "4143000000",
            "otherCurrentLiabilities": "501000000",
            "otherNonCurrentLiabilities": "145000000",
            "totalShareholderEquity": "11455000000",
            "treasuryStock": "None",
            "retainedEarnings": "4413000000",
            "commonStock": "1269000000",
            "commonStockSharesOutstanding": "507762881"
        },
        {
            "fiscalDateEnding": "2017-09-30",
            "reportedCurrency": "USD",
            "totalAssets": "42468794000",
            "totalCurrentAssets": "2898874000",
            "cashAndCashEquivalentsAtCarryingValue": "167000000",
            "cashAndShortTermInvestments": "167841000",
            "inventory": "616675000",
            "currentNetReceivables": "807621000",
            "totalNonCurrentAssets": "37513155000",
            "propertyPlantEquipment": "33949952000",
            "accumulatedDepreciationAmortizationPPE": "14982709000",
            "intangibleAssets": "None",
            "intangibleAssetsExcludingGoodwill": "None",
            "goodwill": "None",
            "investments": "587923000",
            "longTermInvestments": "243500000",
            "shortTermInvestments": "841000",
            "otherCurrentAssets": "681080000",
            "otherNonCurrrentAssets": "259117000",
            "totalLiabilities": "31029417000",
            "totalCurrentLiabilities": "3340406000",
            "currentAccountsPayable": "992498000",
            "deferredRevenue": "None",
            "currentDebt": "819415000",
            "shortTermDebt": "514000000",
            "totalNonCurrentLiabilities": "27689011000",
            "capitalLeaseObligations": "None",
            "longTermDebt": "14572967000",
            "currentLongTermDebt": "305415000",
            "longTermDebtNoncurrent": "None",
            "shortLongTermDebtTotal": "514000000",
            "otherCurrentLiabilities": "486713000",
            "otherNonCurrentLiabilities": "144528000",
            "totalShareholderEquity": "11439377000",
            "treasuryStock": "None",
            "retainedEarnings": "4386050000",
            "commonStock": "1269407000",
            "commonStockSharesOutstanding": "507762881"
        },
        {
            "fiscalDateEnding": "2017-06-30",
            "reportedCurrency": "USD",
            "totalAssets": "41860989000",
            "totalCurrentAssets": "2756550000",
            "cashAndCashEquivalentsAtCarryingValue": "61000000",
            "cashAndShortTermInvestments": "61382000",
            "inventory": "542044000",
            "currentNetReceivables": "759378000",
            "totalNonCurrentAssets": "37117451000",
            "propertyPlantEquipment": "33543843000",
            "accumulatedDepreciationAmortizationPPE": "14703391000",
            "intangibleAssets": "None",
            "intangibleAssetsExcludingGoodwill": "None",
            "goodwill": "None",
            "investments": "449633000",
            "longTermInvestments": "244600000",
            "shortTermInvestments": "382000",
            "otherCurrentAssets": "785247000",
            "otherNonCurrrentAssets": "255470000",
            "totalLiabilities": "30737834000",
            "totalCurrentLiabilities": "3690704000",
            "currentAccountsPayable": "973642000",
            "deferredRevenue": "None",
            "currentDebt": "1289345000",
            "shortTermDebt": "784000000",
            "totalNonCurrentLiabilities": "27047130000",
            "capitalLeaseObligations": "None",
            "longTermDebt": "14091833000",
            "currentLongTermDebt": "505345000",
            "longTermDebtNoncurrent": "None",
            "shortLongTermDebtTotal": "784000000",
            "otherCurrentLiabilities": "439917000",
            "otherNonCurrentLiabilities": "225215000",
            "totalShareholderEquity": "11123155000",
            "treasuryStock": "None",
            "retainedEarnings": "4079068000",
            "commonStock": "1269407000",
            "commonStockSharesOutstanding": "507762881"
        },
        {
            "fiscalDateEnding": "2017-03-31",
            "reportedCurrency": "USD",
            "totalAssets": "41285341000",
            "totalCurrentAssets": "2633154000",
            "cashAndCashEquivalentsAtCarryingValue": "74000000",
            "cashAndShortTermInvestments": "73985000",
            "inventory": "519081000",
            "currentNetReceivables": "781248000",
            "totalNonCurrentAssets": "36699741000",
            "propertyPlantEquipment": "33158384000",
            "accumulatedDepreciationAmortizationPPE": "14576320000",
            "intangibleAssets": "None",
            "intangibleAssetsExcludingGoodwill": "None",
            "goodwill": "None",
            "investments": "417059000",
            "longTermInvestments": "235500000",
            "shortTermInvestments": "None",
            "otherCurrentAssets": "703395000",
            "otherNonCurrrentAssets": "247351000",
            "totalLiabilities": "30215230000",
            "totalCurrentLiabilities": "3707976000",
            "currentAccountsPayable": "861506000",
            "deferredRevenue": "None",
            "currentDebt": "1360448000",
            "shortTermDebt": "605000000",
            "totalNonCurrentLiabilities": "26507254000",
            "capitalLeaseObligations": "None",
            "longTermDebt": "13696461000",
            "currentLongTermDebt": "755448000",
            "longTermDebtNoncurrent": "None",
            "shortLongTermDebtTotal": "605000000",
            "otherCurrentLiabilities": "393489000",
            "otherNonCurrentLiabilities": "235333000",
            "totalShareholderEquity": "11070111000",
            "treasuryStock": "None",
            "retainedEarnings": "4036352000",
            "commonStock": "1269407000",
            "commonStockSharesOutstanding": "507762881"
        }
    ]
}